[
  {
    "label": "hiOcc",
    "shape": [
      131072,
      256
    ],
    "occ": 992.969696969697,
    "seed_M": 8,
    "tc_us": 93.75999867916107,
    "best": "M x2+w16",
    "arms": {
      "seed": {
        "us": 106.01600259542465,
        "spread": 0.0015092176124535787,
        "correct": true
      },
      "M x2+w8": {
        "us": 96.92800045013428,
        "spread": 0.000990433420121487,
        "correct": true
      },
      "M x2+w16": {
        "us": 95.67999839782715,
        "spread": 0.0006689014255776692,
        "correct": true
      },
      "M x4+w8": {
        "us": 101.1200025677681,
        "spread": 0.0009493742934492731,
        "correct": true
      },
      "M x4+w16": {
        "us": 97.34400361776352,
        "spread": 0.000986124227925731,
        "correct": true
      }
    }
  },
  {
    "label": "hiOcc",
    "shape": [
      262144,
      128
    ],
    "occ": 1985.939393939394,
    "seed_M": 16,
    "tc_us": 94.91200000047684,
    "best": "M x2+w16",
    "arms": {
      "seed": {
        "us": 98.94400089979172,
        "spread": 0.001293670899611063,
        "correct": true
      },
      "M x2+w8": {
        "us": 96.12800180912018,
        "spread": 0.00099867602763647,
        "correct": true
      },
      "M x2+w16": {
        "us": 95.64799815416336,
        "spread": 0.0006691252149827651,
        "correct": true
      },
      "M x4+w8": {
        "us": 99.48799759149551,
        "spread": 0.0009649478662295431,
        "correct": true
      },
      "M x4+w16": {
        "us": 95.77599912881851,
        "spread": 0.0006682309546204281,
        "correct": true
      }
    }
  },
  {
    "label": "hiOcc",
    "shape": [
      131072,
      512
    ],
    "occ": 992.969696969697,
    "seed_M": 8,
    "tc_us": 181.88799917697906,
    "best": "M x2+w16",
    "arms": {
      "seed": {
        "us": 238.0480021238327,
        "spread": 0.0008737956515035777,
        "correct": true
      },
      "M x2+w8": {
        "us": 192.1599954366684,
        "spread": 0.0008326070542142192,
        "correct": true
      },
      "M x2+w16": {
        "us": 188.11199814081192,
        "spread": 0.00034022543995129907,
        "correct": true
      },
      "M x4+w8": {
        "us": 217.72800385951996,
        "spread": 0.002204636505312022,
        "correct": true
      },
      "M x4+w16": {
        "us": 248.51199984550476,
        "spread": 0.008241083509750165,
        "correct": true
      }
    }
  },
  {
    "label": "loOcc-control",
    "shape": [
      16384,
      512
    ],
    "occ": 124.12121212121212,
    "seed_M": 1,
    "tc_us": 27.775999158620834,
    "best": "seed",
    "arms": {
      "seed": {
        "us": 29.24799919128418,
        "spread": 0.002188136845323008,
        "correct": true
      },
      "M x2+w8": {
        "us": 29.85600009560585,
        "spread": 0.0010718195190687174,
        "correct": true
      },
      "M x2+w16": {
        "us": 37.28000074625015,
        "spread": 0.004291878087878877,
        "correct": true
      },
      "M x4+w8": {
        "us": 29.279999434947968,
        "spread": 0.002185809035610366,
        "correct": true
      },
      "M x4+w16": {
        "us": 31.10400028526783,
        "spread": 0.0030864432263021015,
        "correct": true
      }
    }
  },
  {
    "label": "loOcc-control",
    "shape": [
      4096,
      256
    ],
    "occ": 31.03030303030303,
    "seed_M": 1,
    "tc_us": 10.208000428974628,
    "best": "M x4+w8",
    "arms": {
      "seed": {
        "us": 9.983999654650688,
        "spread": 0.03205124736969459,
        "correct": true
      },
      "M x2+w8": {
        "us": 10.367999784648418,
        "spread": 0.0030864433187170423,
        "correct": true
      },
      "M x2+w16": {
        "us": 13.055999763309956,
        "spread": 0.009803925065339171,
        "correct": true
      },
      "M x4+w8": {
        "us": 9.472000412642956,
        "spread": 0.003378305632092399,
        "correct": true
      },
      "M x4+w16": {
        "us": 10.751999914646149,
        "spread": 0.008928552867454918,
        "correct": true
      }
    }
  }
]